README.rst
setup.py
chunk2/__init__.py
chunk2.egg-info/PKG-INFO
chunk2.egg-info/SOURCES.txt
chunk2.egg-info/dependency_links.txt
chunk2.egg-info/top_level.txt