Metadata-Version: 1.1
Name: chunk2
Version: 0.1.0
Summary: A replacement Chunk class that allows both reading and writing IFF chunks.
Home-page: https://github.com/darkfoxprime/python-chunk2
Author: Johnson Earls
Author-email: darkfoxprime@gmail.com
License: ISC
Keywords: IFF,chunk,read,write
Platform: UNKNOWN
Classifier: Development Status :: 4 - Beta
Classifier: Intended Audience :: Developers
Classifier: Topic :: Software Development :: Libraries :: Python Modules
Classifier: License :: OSI Approved :: ISC License (ISCL)
Classifier: Programming Language :: Python :: 2.6
Classifier: Programming Language :: Python :: 2.7
